[
  {
    "id": "prophet_01",
    "category": "انبياء",
    "title": "قصة سيدنا آدم عليه السلام",
    "text": "خلق الله آدم من طين، ثم علمه الأسماء كلها، وأمر الملائكة بالسجود له فسجدوا إلا إبليس أبى واستكبر...",
    "source": "سورة البقرة، سورة ص",
    "lessons": ["التواضع", "التوبة", "رحمة الله"],
    "video_url": ""
  },
  {
    "id": "prophet_02",
    "category": "انبياء",
    "title": "قصة سيدنا نوح عليه السلام",
    "text": "بعث الله نوحاً إلى قومه يدعوهم لعبادة الله وحده، فلبث فيهم ألف سنة إلا خمسين عاماً يدعوهم...",
    "source": "سورة نوح، سورة هود",
    "lessons": ["الصبر", "الدعوة", "الثبات"],
    "video_url": ""
  },
  {
    "id": "prophet_03",
    "category": "انبياء",
    "title": "قصة سيدنا إبراهيم عليه السلام",
    "text": "كان إبراهيم يبحث عن ربه، فرأى كوكباً فقال هذا ربي، فلما أفل قال لا أحب الآفلين...",
    "source": "سورة الأنعام، سورة إبراهيم",
    "lessons": ["التوحيد", "التضحية", "الثقة بالله"],
    "video_url": ""
  },
  {
    "id": "prophet_04",
    "category": "انبياء",
    "title": "قصة سيدنا موسى عليه السلام",
    "text": "ولد موسى في وقت كان فرعون يذبح أبناء بني إسرائيل، فأوحى الله إلى أمه أن تلقيه في اليم...",
    "source": "سورة القصص، سورة طه",
    "lessons": ["الثقة بالله", "الشجاعة", "العدل"],
    "video_url": ""
  },
  {
    "id": "prophet_05",
    "category": "انبياء",
    "title": "قصة سيدنا يوسف عليه السلام",
    "text": "رأى يوسف أحد عشر كوكباً والشمس والقمر له ساجدين، فقص رؤياه على أبيه يعقوب...",
    "source": "سورة يوسف",
    "lessons": ["الصبر", "العفة", "التسامح"],
    "video_url": ""
  },
  {
    "id": "woman_01",
    "category": "نساء",
    "title": "قصة آسية بنت مزاحم",
    "text": "امرأة فرعون التي آمنت بالله سراً، وصبرت على أشد أنواع العذاب...",
    "source": "سورة التحريم",
    "lessons": ["الإيمان", "الصبر", "التضحية"],
    "video_url": ""
  },
  {
    "id": "woman_02",
    "category": "نساء",
    "title": "قصة مريم بنت عمران",
    "text": "اصطفاها الله وطهرها واصطفاها على نساء العالمين، وحملت بعيسى عليه السلام معجزة من الله...",
    "source": "سورة آل عمران، سورة مريم",
    "lessons": ["التقوى", "التسليم لله", "العفة"],
    "video_url": ""
  },
  {
    "id": "animal_01",
    "category": "حيوان",
    "title": "قصة حوت يونس",
    "text": "التقم الحوت يونس عليه السلام وهو ملوم، فنادى في الظلمات أن لا إله إلا أنت سبحانك إني كنت من الظالمين...",
    "source": "سورة الأنبياء، سورة الصافات",
    "lessons": ["التوبة", "الدعاء", "رحمة الله"],
    "video_url": ""
  },
  {
    "id": "animal_02",
    "category": "حيوان",
    "title": "قصة هدهد سليمان",
    "text": "تفقد سليمان الطير فقال ما لي لا أرى الهدهد، فأتى الهدهد بخبر مملكة سبأ...",
    "source": "سورة النمل",
    "lessons": ["الملاحظة", "نقل الخير", "الحكمة"],
    "video_url": ""
  },
  {
    "id": "human_01",
    "category": "انسان",
    "title": "قصة لقمان الحكيم",
    "text": "آتاه الله الحكمة، وكان يعظ ابنه بأعظم المواعظ...",
    "source": "سورة لقمان",
    "lessons": ["الحكمة", "بر الوالدين", "التواضع"],
    "video_url": ""
  },
  {
    "id": "nation_01",
    "category": "اقوام",
    "title": "قصة أصحاب الكهف",
    "text": "فتية آمنوا بربهم فزادهم الله هدى، وضرب الله على آذانهم في الكهف سنين عدداً...",
    "source": "سورة الكهف",
    "lessons": ["الثبات على الإيمان", "التوكل", "الأمل"],
    "video_url": ""
  },
  {
    "id": "nation_02",
    "category": "اقوام",
    "title": "قصة قوم عاد وثمود",
    "text": "أرسل الله هوداً إلى عاد وصالحاً إلى ثمود، فكفروا وعصوا فأهلكهم الله...",
    "source": "سورة هود، سورة الأعراف",
    "lessons": ["العبرة", "الاستكبار", "عاقبة الكفر"],
    "video_url": ""
  }
]
